libcrypto.so
libssl.so
boringssl_binary_build.libs/libstdc++-0d31ccbe.so.6.0.32
boringssl_binary_build.libs/libgcc_s-a0b57c20.so.1
boringssl_binary_build.libs/libcrypto-24b6eb34.so
boringssl_binary_build-0.0.6.dist-info/top_level.txt
boringssl_binary_build-0.0.6.dist-info/RECORD
boringssl_binary_build-0.0.6.dist-info/METADATA
boringssl_binary_build-0.0.6.dist-info/WHEEL
