Metadata-Version: 2.1
Name: boringssl-binary-build
Version: 0.0.6
Summary: Build and bundle BoringSSL
Author: boring
Author-email: boring@gmail.com
Requires-Python: >=3.10
